<annotation>
	<folder>JPEGImages</folder>
	<filename>0175-90_77-180&amp;404_421&amp;492-439&amp;491_178&amp;479_166&amp;395_427&amp;407-0_0_11_29_31_24_22-118-43.jpg</filename>
	<path>D:\Desktop\CCPD2020\VOCdevkit\VOC2007\JPEGImages\0175-90_77-180&amp;404_421&amp;492-439&amp;491_178&amp;479_166&amp;395_427&amp;407-0_0_11_29_31_24_22-118-43.jpg</path>
	<source>
		<database>Unknown</database>
	</source>
	<size>
		<width>720</width>
		<height>1160</height>
		<depth>3</depth>
	</size>
	<segmented>0</segmented>
	<object>
		<name>plate</name>
		<pose>Unspecified</pose>
		<truncated>0</truncated>
		<difficult>0</difficult>
		<bndbox>
			<xmin>156</xmin>
			<ymin>389</ymin>
			<xmax>434</xmax>
			<ymax>498</ymax>
		</bndbox>
	</object>
</annotation>
