<annotation>
	<folder>JPEGImages</folder>
	<filename>021015625-90_92-192&amp;439_461&amp;518-461&amp;516_196&amp;518_192&amp;442_459&amp;439-0_0_3_24_24_31_24_32-122-229.jpg</filename>
	<path>D:\Desktop\CCPD2020\VOCdevkit\VOC2007\JPEGImages\021015625-90_92-192&amp;439_461&amp;518-461&amp;516_196&amp;518_192&amp;442_459&amp;439-0_0_3_24_24_31_24_32-122-229.jpg</path>
	<source>
		<database>Unknown</database>
	</source>
	<size>
		<width>720</width>
		<height>1160</height>
		<depth>3</depth>
	</size>
	<segmented>0</segmented>
	<object>
		<name>plate</name>
		<pose>Unspecified</pose>
		<truncated>0</truncated>
		<difficult>0</difficult>
		<bndbox>
			<xmin>180</xmin>
			<ymin>421</ymin>
			<xmax>482</xmax>
			<ymax>539</ymax>
		</bndbox>
	</object>
</annotation>
