<annotation>
	<folder>JPEGImages</folder>
	<filename>02125-90_257-175&amp;388_447&amp;467-447&amp;467_190&amp;465_175&amp;389_439&amp;388-0_0_3_25_30_29_29_32-106-15.jpg</filename>
	<path>D:\Desktop\CCPD2020\VOCdevkit\VOC2007\JPEGImages\02125-90_257-175&amp;388_447&amp;467-447&amp;467_190&amp;465_175&amp;389_439&amp;388-0_0_3_25_30_29_29_32-106-15.jpg</path>
	<source>
		<database>Unknown</database>
	</source>
	<size>
		<width>720</width>
		<height>1160</height>
		<depth>3</depth>
	</size>
	<segmented>0</segmented>
	<object>
		<name>plate</name>
		<pose>Unspecified</pose>
		<truncated>0</truncated>
		<difficult>0</difficult>
		<bndbox>
			<xmin>162</xmin>
			<ymin>366</ymin>
			<xmax>470</xmax>
			<ymax>486</ymax>
		</bndbox>
	</object>
</annotation>
