<annotation>
	<folder>JPEGImages</folder>
	<filename>0225-91_73-201&amp;495_497&amp;593-517&amp;604_229&amp;590_191&amp;493_479&amp;507-0_0_1_29_29_29_22-128-37.jpg</filename>
	<path>D:\Desktop\CCPD2020\VOCdevkit\VOC2007\JPEGImages\0225-91_73-201&amp;495_497&amp;593-517&amp;604_229&amp;590_191&amp;493_479&amp;507-0_0_1_29_29_29_22-128-37.jpg</path>
	<source>
		<database>Unknown</database>
	</source>
	<size>
		<width>720</width>
		<height>1160</height>
		<depth>3</depth>
	</size>
	<segmented>0</segmented>
	<object>
		<name>plate</name>
		<pose>Unspecified</pose>
		<truncated>0</truncated>
		<difficult>0</difficult>
		<bndbox>
			<xmin>182</xmin>
			<ymin>481</ymin>
			<xmax>536</xmax>
			<ymax>616</ymax>
		</bndbox>
	</object>
</annotation>
