<annotation>
	<folder>JPEGImages</folder>
	<filename>03-97_82-195&amp;444_456&amp;568-457&amp;595_203&amp;550_210&amp;436_464&amp;481-0_0_31_16_24_31_24-164-49.jpg</filename>
	<path>D:\Desktop\CCPD2020\VOCdevkit\VOC2007\JPEGImages\03-97_82-195&amp;444_456&amp;568-457&amp;595_203&amp;550_210&amp;436_464&amp;481-0_0_31_16_24_31_24-164-49.jpg</path>
	<source>
		<database>Unknown</database>
	</source>
	<size>
		<width>720</width>
		<height>1160</height>
		<depth>3</depth>
	</size>
	<segmented>0</segmented>
	<object>
		<name>plate</name>
		<pose>Unspecified</pose>
		<truncated>0</truncated>
		<difficult>0</difficult>
		<bndbox>
			<xmin>206</xmin>
			<ymin>437</ymin>
			<xmax>475</xmax>
			<ymax>602</ymax>
		</bndbox>
	</object>
</annotation>
